literary.pth
literary/__init__.py
literary/commands/__init__.py
literary/commands/__main__.py
literary/commands/app.py
literary/commands/build.py
literary/commands/test.py
literary/commands/trait.py
literary/config/__init__.py
literary/hook/__init__.py
literary/hook/finder.py
literary/hook/importer.py
literary/hook/loader.py
literary/module/__init__.py
literary/notebook/__init__.py
literary/transpile/__init__.py
literary/transpile/exporter.py
literary/transpile/filter.py
literary/transpile/patch.py
literary/transpile/preprocessor.py
literary/transpile/syntax.py
literary-4.0.2.data/data/share/jupyter/nbconvert/templates/literary/conf.json
literary-4.0.2.data/data/share/jupyter/nbconvert/templates/literary/index.py.j2
literary-4.0.2.dist-info/METADATA
literary-4.0.2.dist-info/WHEEL
literary-4.0.2.dist-info/entry_points.txt
literary-4.0.2.dist-info/licenses/LICENSE
literary-4.0.2.dist-info/RECORD
