Metadata-Version: 2.4
Name: literary
Version: 4.0.2
Summary: Literate package development with Jupyter
Project-URL: Repository, http://github.com/agoose77/literary
Project-URL: Bug Tracker, http://github.com/agoose77/literary/issues
Author-email: Angus Hollands <goosey15@gmail.com>
License: BSD 3-Clause License
License-File: LICENSE
Keywords: jupyter,literate-programming,nbconvert,notebooks
Classifier: Development Status :: 4 - Beta
Classifier: Intended Audience :: Developers
Classifier: Intended Audience :: Science/Research
Classifier: License :: OSI Approved :: BSD License
Classifier: Operating System :: OS Independent
Classifier: Programming Language :: Python
Classifier: Programming Language :: Python :: 3
Classifier: Programming Language :: Python :: 3 :: Only
Classifier: Programming Language :: Python :: 3.9
Classifier: Programming Language :: Python :: 3.10
Classifier: Programming Language :: Python :: 3.11
Classifier: Programming Language :: Python :: 3.12
Classifier: Programming Language :: Python :: 3.13
Requires-Python: >=3.9
Requires-Dist: ipython>=7.33
Requires-Dist: jupyter-core>=4.7
Requires-Dist: nbclient>=0.5.12
Requires-Dist: nbconvert>=6.0
Requires-Dist: nbformat>=5.10
Requires-Dist: traitlets>=5
Requires-Dist: typing-extensions>=3.10
